{
  "skills": [
    {
      "name": "Debugging issues",
      "tags": [
        "JavaScript",
        "TypeScript",
        "Swift",
        "Objective-C",
        "React",
        "SwiftUI",
        "UIKit",
        "Node.js",
        "jQuery",
        "Core Data",
        "TDD",
        "Git",
        "GitHub",
        "Python"
      ],
      "category": [
        "Web Development",
        "Mobile Development",
        "Database and APIs",
        "Testing and Version Control"
      ]
    },
    {
      "name": "JavaScript",
      "tags": [
        "Identifying and debugging issues",
        "React",
        "Node.js",
        "jQuery",
        "npm",
        "TDD",
        "Git",
        "GitHub"
      ],
      "category": [
        "Web Development"
      ]
    },
    {
      "name": "TypeScript",
      "tags": [
        "Identifying and debugging issues",
        "React",
        "Node.js",
        "TDD",
        "Git",
        "GitHub"
      ],
      "category": [
        "Web Development"
      ]
    },
    {
      "name": "Swift",
      "tags": [
        "Identifying and debugging issues",
        "SwiftUI",
        "Objective-C",
        "UIKit",
        "Core Data",
        "Git",
        "GitHub"
      ],
      "category": [
        "Mobile Development"
      ]
    },
    {
      "name": "Objective-C",
      "tags": [
        "Identifying and debugging issues",
        "Swift",
        "UIKit",
        "Core Data",
        "Git",
        "GitHub"
      ],
      "category": [
        "Mobile Development"
      ]
    },
    {
      "name": "React",
      "tags": [
        "Identifying and debugging issues",
        "JavaScript",
        "TypeScript",
        "Tailwind",
        "HTML",
        "CSS",
        "Responsive design",
        "Git",
        "GitHub"
      ],
      "category": [
        "Web Development",
        "Design and Styling",
        "Testing and Version Control"
      ]
    },
    {
      "name": "Tailwind",
      "tags": [
        "React",
        "HTML",
        "CSS",
        "Responsive design"
      ],
      "category": [
        "Design and Styling"
      ]
    },
    {
      "name": "HTML",
      "tags": [
        "React",
        "Tailwind",
        "CSS",
        "Responsive design"
      ],
      "category": []
    },
    {
      "name": "CSS",
      "tags": [
        "React",
        "Tailwind",
        "HTML",
        "Responsive design"
      ],
      "category": []
    },
    {
      "name": "SwiftUI",
      "tags": [
        "Swift",
        "Git",
        "GitHub"
      ],
      "category": []
    },
    {
      "name": "MongoDB",
      "tags": [
        "RESTful API"
      ],
      "category": []
    },
    {
      "name": "SQL",
      "tags": [
        "RESTful API"
      ],
      "category": []
    },
    {
      "name": "RESTful API",
      "tags": [
        "JavaScript",
        "MongoDB",
        "SQL"
      ],
      "category": []
    },
    {
      "name": "KMM",
      "tags": [],
      "category": []
    },
    {
      "name": "UIKit",
      "tags": [
        "Swift",
        "Objective-C",
        "Git",
        "GitHub"
      ],
      "category": []
    },
    {
      "name": "Node.js",
      "tags": [
        "JavaScript",
        "TypeScript",
        "Git",
        "GitHub"
      ],
      "category": []
    },
    {
      "name": "jQuery",
      "tags": [
        "JavaScript",
        "Git",
        "GitHub"
      ],
      "category": []
    },
    {
      "name": "npm",
      "tags": [
        "JavaScript",
        "Git",
        "GitHub"
      ],
      "category": []
    },
    {
      "name": "Core Data",
      "tags": [
        "Swift",
        "Objective-C",
        "Git",
        "GitHub"
      ],
      "category": []
    },
    {
      "name": "TDD",
      "tags": [
        "JavaScript",
        "TypeScript",
        "Git",
        "GitHub"
      ],
      "category": []
    },
    {
      "name": "Responsive design",
      "tags": [
        "JavaScript",
        "TypeScript",
        "React",
        "Tailwind",
        "HTML",
        "CSS"
      ],
      "category": []
    },
    {
      "name": "Git",
      "tags": [
        "JavaScript",
        "TypeScript",
        "Swift",
        "Objective-C",
        "React",
        "SwiftUI",
        "UIKit",
        "Node.js",
        "jQuery",
        "npm",
        "Core Data",
        "TDD",
        "Responsive design"
      ],
      "category": []
    },
    {
      "name": "GitHub",
      "tags": [
        "JavaScript",
        "TypeScript",
        "Swift",
        "Objective-C",
        "React",
        "SwiftUI",
        "UIKit",
        "Node.js",
        "jQuery",
        "npm",
        "Core Data",
        "TDD",
        "Responsive design"
      ],
      "category": []
    },
    {
      "name": "Python",
      "tags": [
        "Identifying and debugging issues",
        "Git",
        "GitHub"
      ],
      "category": []
    },
    {
      "name": "Adaptability",
      "tags": [
        "Teamwork",
        "Empathy",
        "Collaboration",
        "Patience",
        "Critical thinking"
      ],
      "category": []
    },
    {
      "name": "Time management",
      "tags": [
        "Organisation"
      ],
      "category": []
    },
    {
      "name": "Problem-solving",
      "tags": [
        "Attention to detail",
        "Critical thinking"
      ],
      "category": []
    },
    {
      "name": "Attention to detail",
      "tags": [
        "Problem-solving",
        "Critical thinking"
      ],
      "category": []
    },
    {
      "name": "Organisation",
      "tags": [
        "Time management"
      ],
      "category": []
    },
    {
      "name": "Teamwork",
      "tags": [
        "Empathy",
        "Collaboration",
        "Patience",
        "Adaptability"
      ],
      "category": []
    },
    {
      "name": "Empathy",
      "tags": [
        "Teamwork",
        "Collaboration",
        "Patience",
        "Adaptability"
      ],
      "category": []
    },
    {
      "name": "Collaboration",
      "tags": [
        "Teamwork",
        "Empathy",
        "Patience",
        "Adaptability"
      ],
      "category": []
    },
    {
      "name": "Patience",
      "tags": [
        "Teamwork",
        "Empathy",
        "Collaboration",
        "Adaptability"
      ],
      "category": []
    },
    {
      "name": "Critical thinking",
      "tags": [
        "Adaptability",
        "Problem-solving",
        "Attention to detail"
      ],
      "category": []
    }
  ]
}
